src/__init__.py
ms_oscar_flash_offer-0.0.0.dist-info/LICENSE
ms_oscar_flash_offer-0.0.0.dist-info/METADATA
ms_oscar_flash_offer-0.0.0.dist-info/WHEEL
ms_oscar_flash_offer-0.0.0.dist-info/top_level.txt
ms_oscar_flash_offer-0.0.0.dist-info/RECORD
