Metadata-Version: 2.1
Name: ms-oscar-flash-offer
Version: 0.0.0
Summary: Django oscar module to create flash offer
Home-page: https://bitbucket.org/jojomakingscience/ms_oscar_flash_offer/
Author: Making Science
Author-email: makingscience@makingscience.com
License: UNKNOWN
Platform: UNKNOWN
Classifier: Operating System :: POSIX :: Linux
Classifier: License :: OSI Approved :: MIT License
Classifier: Programming Language :: Python :: 3.5
Classifier: Programming Language :: Python :: 3.6
Classifier: Programming Language :: Python :: 3.7
